niwrap_freesurfer/freesurfer/__init__.py
niwrap_freesurfer/freesurfer/analyzeto4dfp.py
niwrap_freesurfer/freesurfer/anatomi_cuts_utils.py
niwrap_freesurfer/freesurfer/annot2std.py
niwrap_freesurfer/freesurfer/ants_denoise_image_fs.py
niwrap_freesurfer/freesurfer/ants_n4_bias_field_correction_fs.py
niwrap_freesurfer/freesurfer/aparc2feat.py
niwrap_freesurfer/freesurfer/aparc_stats_aseg.py
niwrap_freesurfer/freesurfer/aparcstats2table.py
niwrap_freesurfer/freesurfer/aparcstatsdiff.py
niwrap_freesurfer/freesurfer/apas2aseg.py
niwrap_freesurfer/freesurfer/apply_morph.py
niwrap_freesurfer/freesurfer/aseg2feat.py
niwrap_freesurfer/freesurfer/asegstats2table.py
niwrap_freesurfer/freesurfer/asegstatsdiff.py
niwrap_freesurfer/freesurfer/avi2talxfm.py
niwrap_freesurfer/freesurfer/bblabel.py
niwrap_freesurfer/freesurfer/bbmask.py
niwrap_freesurfer/freesurfer/bbregister.py
niwrap_freesurfer/freesurfer/bedpostx_mgh.py
niwrap_freesurfer/freesurfer/beta2sxa.py
niwrap_freesurfer/freesurfer/biasfield.py
niwrap_freesurfer/freesurfer/bmedits2surf.py
niwrap_freesurfer/freesurfer/brec.py
niwrap_freesurfer/freesurfer/browse_minc_header_tcl.py
niwrap_freesurfer/freesurfer/bugr.py
niwrap_freesurfer/freesurfer/build_desikan_killiany_gcs_csh.py
niwrap_freesurfer/freesurfer/cblumwmgyri.py
niwrap_freesurfer/freesurfer/check_mcr_sh.py
niwrap_freesurfer/freesurfer/check_recons_sh.py
niwrap_freesurfer/freesurfer/check_subject.py
niwrap_freesurfer/freesurfer/compute_interrater_variability_csh.py
niwrap_freesurfer/freesurfer/compute_label_volumes_csh.py
niwrap_freesurfer/freesurfer/compute_vox2vox.py
niwrap_freesurfer/freesurfer/conf2hires.py
niwrap_freesurfer/freesurfer/connected_components.py
niwrap_freesurfer/freesurfer/cor_to_minc.py
niwrap_freesurfer/freesurfer/cp_dicom.py
niwrap_freesurfer/freesurfer/create_morph.py
niwrap_freesurfer/freesurfer/csvprint.py
niwrap_freesurfer/freesurfer/dcmdir_info_mgh.py
niwrap_freesurfer/freesurfer/dcmdjpeg_fs.py
niwrap_freesurfer/freesurfer/dcmdrle_fs.py
niwrap_freesurfer-0.8.3.dist-info/WHEEL
niwrap_freesurfer-0.8.3.dist-info/METADATA
niwrap_freesurfer-0.8.3.dist-info/RECORD
